setup.py
probability_tools/Binomialdistribution.py
probability_tools/Gaussiandistribution.py
probability_tools/Generaldistribution.py
probability_tools/__init__.py
probability_tools.egg-info/PKG-INFO
probability_tools.egg-info/SOURCES.txt
probability_tools.egg-info/dependency_links.txt
probability_tools.egg-info/not-zip-safe
probability_tools.egg-info/top_level.txt