Metadata-Version: 2.1
Name: probability_tools
Version: 1.0
Summary: Gaussian and binomial distributions
Author: Hesam Najafi
Author-email: hesamnajafi39@gmail.com
